asyncio_dgram/__init__.py
asyncio_dgram/aio.py
asyncio_dgram/aio.pyi
asyncio_dgram/py.typed
asyncio_dgram-2.2.0.dist-info/LICENSE
asyncio_dgram-2.2.0.dist-info/METADATA
asyncio_dgram-2.2.0.dist-info/WHEEL
asyncio_dgram-2.2.0.dist-info/top_level.txt
asyncio_dgram-2.2.0.dist-info/RECORD
