Metadata-Version: 2.1
Name: asyncio-dgram
Version: 2.2.0
Summary: Higher level Datagram support for Asyncio
Home-page: https://github.com/jsbronder/asyncio-dgram
Author: Justin Bronder
Author-email: jsbronder@cold-front.org
License: MIT
Classifier: Development Status :: 5 - Production/Stable
Classifier: Intended Audience :: Developers
Classifier: Framework :: AsyncIO
Classifier: License :: OSI Approved :: MIT License
Classifier: Programming Language :: Python :: 3.6
Classifier: Programming Language :: Python :: 3.7
Classifier: Programming Language :: Python :: 3.8
Classifier: Programming Language :: Python :: 3.9
Classifier: Programming Language :: Python :: 3.10
Classifier: Programming Language :: Python :: 3.11
Classifier: Programming Language :: Python :: 3.12
Requires-Python: >=3.6
Provides-Extra: test
License-File: LICENSE
